{
	"todos": [
		{
			"id": "5cc3",
			"title": "nakarmić kota "
		},
		{
			"id": "a944",
			"title": "bawić się z kotem "
		},
		{
			"id": "02fe",
			"title": "wyczesać kota "
		},
		{
			"id": "ac2b",
			"title": "fffff"
		},
		{
			"id": "2751",
			"title": "hsjdfds"
		},
		{
			"id": "4756",
			"title": "okt liasa "
		}
	],
	"subtodos": [
		{
			"todoId": "5cc3",
			"id": "aaaa",
			"title": "karmą z tuńczykiem"
		},
		{
			"todoId": "5cc3",
			"id": "aeea",
			"title": "2karmą z tuńczykiem"
		},
		{
			"todoId": "5cc3",
			"id": "aafdaa",
			"title": "3karmą z tuńczykiem"
		},
		{
			"todoId": "a944",
			"id": "bbbb",
			"title": "piłeczką do tenisa"
		},
		{
			"todoId": "02fe",
			"id": "cccc",
			"title": "szczotką"
		}
	]
}
